{"province":{"code":"19สระบุรี","labelEn":"สระบุรี","labelTh":"สระบุรี"},"districts":[{"code":"1901เมืองสระบุรี","labelEn":"Mueang Saraburi","labelTh":"เมืองสระบุรี","postalCodes":["18000"],"subDistricts":[{"code":"190114ตะกุด","labelEn":"Takut","labelTh":"ตะกุด"},{"code":"190101ปากเพรียว","labelEn":"ปากเพรียว","labelTh":"ปากเพรียว"},{"code":"190105ดาวเรือง","labelEn":"Dao Rueang","labelTh":"ดาวเรือง"},{"code":"190106นาโฉง","labelEn":"Na Chong","labelTh":"นาโฉง"},{"code":"190107โคกสว่าง","labelEn":"Khok Sawang","labelTh":"โคกสว่าง"},{"code":"190108หนองโน","labelEn":"Nong No","labelTh":"หนองโน"},{"code":"190109หนองยาว","labelEn":"Nong Yao","labelTh":"หนองยาว"},{"code":"190110ปากข้าวสาร","labelEn":"ปากข้าวสาร","labelTh":"ปากข้าวสาร"},{"code":"190111หนองปลาไหล","labelEn":"Nong Pla Lai","labelTh":"หนองปลาไหล"},{"code":"190112กุดนกเปล้า","labelEn":"Kut Nok Plao","labelTh":"กุดนกเปล้า"},{"code":"190113ตลิ่งชัน","labelEn":"Taling Chan","labelTh":"ตลิ่งชัน"}]},{"code":"1902แก่งคอย","labelEn":"Kaeng Khoi","labelTh":"แก่งคอย","postalCodes":["18110","18260"],"subDistricts":[{"code":"190201แก่งคอย","labelEn":"Kaeng Khoi","labelTh":"แก่งคอย"},{"code":"190202ทับกวาง","labelEn":"Thap Kwang","labelTh":"ทับกวาง"},{"code":"190203ตาลเดี่ยว","labelEn":"Tan Diao","labelTh":"ตาลเดี่ยว"},{"code":"190204ห้วยแห้ง","labelEn":"Huai Haeng","labelTh":"ห้วยแห้ง"},{"code":"190205ท่าคล้อ","labelEn":"Tha Khlo","labelTh":"ท่าคล้อ"},{"code":"190206หินซ้อน","labelEn":"Hin Son","labelTh":"หินซ้อน"},{"code":"190207บ้านธาตุ","labelEn":"บ้านธาตุ","labelTh":"บ้านธาตุ"},{"code":"190208บ้านป่า","labelEn":"Ban Pa","labelTh":"บ้านป่า"},{"code":"190209ท่าตูม","labelEn":"Tha Tum","labelTh":"ท่าตูม"},{"code":"190210ชะอม","labelEn":"ชะอม","labelTh":"ชะอม"},{"code":"190211สองคอน","labelEn":"สองคอน","labelTh":"สองคอน"},{"code":"190212เตาปูน","labelEn":"Tao Pun","labelTh":"เตาปูน"},{"code":"190213ชำผักแพว","labelEn":"Cham Phak Phaeo","labelTh":"ชำผักแพว"},{"code":"190215ท่ามะปราง","labelEn":"Tha Maprang","labelTh":"ท่ามะปราง"}]},{"code":"1903หนองแค","labelEn":"หนองแค","labelTh":"หนองแค","postalCodes":["18140","18230","18250"],"subDistricts":[{"code":"190301หนองแค","labelEn":"Nong Khae","labelTh":"หนองแค"},{"code":"190302กุ่มหัก","labelEn":"กุ่มหัก","labelTh":"กุ่มหัก"},{"code":"190303คชสิทธิ์","labelEn":"Khotchasit","labelTh":"คชสิทธิ์"},{"code":"190304โคกตูม","labelEn":"Khok Tum","labelTh":"โคกตูม"},{"code":"190305โคกแย้","labelEn":"Khok Yae","labelTh":"โคกแย้"},{"code":"190306บัวลอย","labelEn":"บัวลอย","labelTh":"บัวลอย"},{"code":"190307ไผ่ต่ำ","labelEn":"Phai Tam","labelTh":"ไผ่ต่ำ"},{"code":"190308โพนทอง","labelEn":"โพนทอง","labelTh":"โพนทอง"},{"code":"190309ห้วยขมิ้น","labelEn":"Huai Khamin","labelTh":"ห้วยขมิ้น"},{"code":"190310ห้วยทราย","labelEn":"Huai Sai","labelTh":"ห้วยทราย"},{"code":"190311หนองไข่น้ำ","labelEn":"Nong Khai Nam","labelTh":"หนองไข่น้ำ"},{"code":"190312หนองแขม","labelEn":"Nong Khaem","labelTh":"หนองแขม"},{"code":"190313หนองจิก","labelEn":"Nong Chik","labelTh":"หนองจิก"},{"code":"190314หนองจรเข้","labelEn":"Nong Chorakhe","labelTh":"หนองจรเข้"},{"code":"190315หนองนาก","labelEn":"Nong Nak","labelTh":"หนองนาก"},{"code":"190316หนองปลาหมอ","labelEn":"Nong Pla Mo","labelTh":"หนองปลาหมอ"},{"code":"190317หนองปลิง","labelEn":"Nong Pling","labelTh":"หนองปลิง"},{"code":"190318หนองโรง","labelEn":"Nong Rong","labelTh":"หนองโรง"}]},{"code":"1904วิหารแดง","labelEn":"วิหารแดง","labelTh":"วิหารแดง","postalCodes":["18150"],"subDistricts":[{"code":"190401หนองหมู","labelEn":"Nong Mu","labelTh":"หนองหมู"},{"code":"190402บ้านลำ","labelEn":"Ban Lam","labelTh":"บ้านลำ"},{"code":"190403คลองเรือ","labelEn":"Khlong Ruea","labelTh":"คลองเรือ"},{"code":"190404วิหารแดง","labelEn":"Wihan Daeng","labelTh":"วิหารแดง"},{"code":"190405หนองสรวง","labelEn":"Nong Suang","labelTh":"หนองสรวง"},{"code":"190406เจริญธรรม","labelEn":"Charoen Tham","labelTh":"เจริญธรรม"}]},{"code":"1905หนองแซง","labelEn":"หนองแซง","labelTh":"หนองแซง","postalCodes":["18170"],"subDistricts":[{"code":"190501หนองแซง","labelEn":"Nong Saeng","labelTh":"หนองแซง"},{"code":"190502หนองควายโซ","labelEn":"Nong Khwai So","labelTh":"หนองควายโซ"},{"code":"190503หนองหัวโพ","labelEn":"Nong Hua Pho","labelTh":"หนองหัวโพ"},{"code":"190504หนองสีดา","labelEn":"Nong Sida","labelTh":"หนองสีดา"},{"code":"190505หนองกบ","labelEn":"Nong Kop","labelTh":"หนองกบ"},{"code":"190506ไก่เส่า","labelEn":"Kai Sao","labelTh":"ไก่เส่า"},{"code":"190507โคกสะอาด","labelEn":"โคกสะอาด","labelTh":"โคกสะอาด"},{"code":"190508ม่วงหวาน","labelEn":"ม่วงหวาน","labelTh":"ม่วงหวาน"},{"code":"190509เขาดิน","labelEn":"Khao Din","labelTh":"เขาดิน"}]},{"code":"1906บ้านหมอ","labelEn":"Ban Mo","labelTh":"บ้านหมอ","postalCodes":["18130","18270"],"subDistricts":[{"code":"190601บ้านหมอ","labelEn":"บ้านหมอ","labelTh":"บ้านหมอ"},{"code":"190602บางโขมด","labelEn":"Bang Khamot","labelTh":"บางโขมด"},{"code":"190603สร่างโศก","labelEn":"Sang Sok","labelTh":"สร่างโศก"},{"code":"190604ตลาดน้อย","labelEn":"Talat Noi","labelTh":"ตลาดน้อย"},{"code":"190605หรเทพ","labelEn":"หรเทพ","labelTh":"หรเทพ"},{"code":"190606โคกใหญ่","labelEn":"Khok Yai","labelTh":"โคกใหญ่"},{"code":"190607ไผ่ขวาง","labelEn":"Phai Khwang","labelTh":"ไผ่ขวาง"},{"code":"190608บ้านครัว","labelEn":"Ban Khrua","labelTh":"บ้านครัว"},{"code":"190609หนองบัว","labelEn":"Nong Bua","labelTh":"หนองบัว"}]},{"code":"1907ดอนพุด","labelEn":"ดอนพุด","labelTh":"ดอนพุด","postalCodes":["18210"],"subDistricts":[{"code":"190701ดอนพุด","labelEn":"Don Phut","labelTh":"ดอนพุด"},{"code":"190702ไผ่หลิ่ว","labelEn":"Phai Lio","labelTh":"ไผ่หลิ่ว"},{"code":"190703บ้านหลวง","labelEn":"Ban Luang","labelTh":"บ้านหลวง"},{"code":"190704ดงตะงาว","labelEn":"Dong Ta Ngao","labelTh":"ดงตะงาว"}]},{"code":"1908หนองโดน","labelEn":"Nong Don","labelTh":"หนองโดน","postalCodes":["18190"],"subDistricts":[{"code":"190801หนองโดน","labelEn":"Nong Don","labelTh":"หนองโดน"},{"code":"190802บ้านกลับ","labelEn":"Ban Klap","labelTh":"บ้านกลับ"},{"code":"190803ดอนทอง","labelEn":"ดอนทอง","labelTh":"ดอนทอง"},{"code":"190804บ้านโปร่ง","labelEn":"Ban Prong","labelTh":"บ้านโปร่ง"}]},{"code":"1909พระพุทธบาท","labelEn":"Phra Phutthabat","labelTh":"พระพุทธบาท","postalCodes":["18120"],"subDistricts":[{"code":"190907ห้วยป่าหวาย","labelEn":"Huai Pa Wai","labelTh":"ห้วยป่าหวาย"},{"code":"190908พุกร่าง","labelEn":"พุกร่าง","labelTh":"พุกร่าง"},{"code":"190909หนองแก","labelEn":"Nong Kae","labelTh":"หนองแก"},{"code":"190901พระพุทธบาท","labelEn":"พระพุทธบาท","labelTh":"พระพุทธบาท"},{"code":"190902ขุนโขลน","labelEn":"ขุนโขลน","labelTh":"ขุนโขลน"},{"code":"190903ธารเกษม","labelEn":"Than Kasem","labelTh":"ธารเกษม"},{"code":"190904นายาว","labelEn":"นายาว","labelTh":"นายาว"},{"code":"190905พุคำจาน","labelEn":"Phu Kham Chan","labelTh":"พุคำจาน"},{"code":"190906เขาวง","labelEn":"Khao Wong","labelTh":"เขาวง"}]},{"code":"1910เสาไห้","labelEn":"Sao Hai","labelTh":"เสาไห้","postalCodes":["18160"],"subDistricts":[{"code":"191002บ้านยาง","labelEn":"Ban Yang","labelTh":"บ้านยาง"},{"code":"191003หัวปลวก","labelEn":"Hua Pluak","labelTh":"หัวปลวก"},{"code":"191004งิ้วงาม","labelEn":"งิ้วงาม","labelTh":"งิ้วงาม"},{"code":"191001เสาไห้","labelEn":"Sao Hai","labelTh":"เสาไห้"},{"code":"191005ศาลารีไทย","labelEn":"Sala Ri Thai","labelTh":"ศาลารีไทย"},{"code":"191006ต้นตาล","labelEn":"ต้นตาล","labelTh":"ต้นตาล"},{"code":"191007ท่าช้าง","labelEn":"ท่าช้าง","labelTh":"ท่าช้าง"},{"code":"191008พระยาทด","labelEn":"Phraya Thot","labelTh":"พระยาทด"},{"code":"191009ม่วงงาม","labelEn":"Muang Ngam","labelTh":"ม่วงงาม"},{"code":"191010เริงราง","labelEn":"Roeng Rang","labelTh":"เริงราง"},{"code":"191011เมืองเก่า","labelEn":"Mueang Kao","labelTh":"เมืองเก่า"},{"code":"191012สวนดอกไม้","labelEn":"Suan Dok Mai","labelTh":"สวนดอกไม้"}]},{"code":"1911มวกเหล็ก","labelEn":"Muak Lek","labelTh":"มวกเหล็ก","postalCodes":["18180","18220","30130"],"subDistricts":[{"code":"191101มวกเหล็ก","labelEn":"Muak Lek","labelTh":"มวกเหล็ก"},{"code":"191102มิตรภาพ","labelEn":"Mittraphap","labelTh":"มิตรภาพ"},{"code":"191104หนองย่างเสือ","labelEn":"Nong Yang Suea","labelTh":"หนองย่างเสือ"},{"code":"191105ลำสมพุง","labelEn":"Lam Somphung","labelTh":"ลำสมพุง"},{"code":"191107ลำพญากลาง","labelEn":"Lam Phaya Klang","labelTh":"ลำพญากลาง"},{"code":"191109ซับสนุ่น","labelEn":"Sap Sanun","labelTh":"ซับสนุ่น"}]},{"code":"1912วังม่วง","labelEn":"วังม่วง","labelTh":"วังม่วง","postalCodes":["18220"],"subDistricts":[{"code":"191201แสลงพัน","labelEn":"แสลงพัน","labelTh":"แสลงพัน"},{"code":"191202คำพราน","labelEn":"Kham Phran","labelTh":"คำพราน"},{"code":"191203วังม่วง","labelEn":"Wang Muang","labelTh":"วังม่วง"}]},{"code":"1913เฉลิมพระเกียรติ","labelEn":"Chaloem Phra Kiat","labelTh":"เฉลิมพระเกียรติ","postalCodes":["18000","18240"],"subDistricts":[{"code":"191301เขาดินพัฒนา","labelEn":"เขาดินพัฒนา","labelTh":"เขาดินพัฒนา"},{"code":"191302บ้านแก้ง","labelEn":"Ban Kaeng","labelTh":"บ้านแก้ง"},{"code":"191303ผึ้งรวง","labelEn":"Phueng Ruang","labelTh":"ผึ้งรวง"},{"code":"191304พุแค","labelEn":"พุแค","labelTh":"พุแค"},{"code":"191305ห้วยบง","labelEn":"Huai Bong","labelTh":"ห้วยบง"},{"code":"191306หน้าพระลาน","labelEn":"Na Phra Lan","labelTh":"หน้าพระลาน"}]}]}