{"province":{"code":"64สุโขทัย","labelEn":"Sukhothai","labelTh":"สุโขทัย"},"districts":[{"code":"6401เมืองสุโขทัย","labelEn":"Mueang Sukhothai","labelTh":"เมืองสุโขทัย","postalCodes":["64000","64210","64220"],"subDistricts":[{"code":"640101ธานี","labelEn":"ธานี","labelTh":"ธานี"},{"code":"640102บ้านสวน","labelEn":"Ban Suan","labelTh":"บ้านสวน"},{"code":"640103เมืองเก่า","labelEn":"Mueang Kao","labelTh":"เมืองเก่า"},{"code":"640104ปากแคว","labelEn":"Pak Khwae","labelTh":"ปากแคว"},{"code":"640105ยางซ้าย","labelEn":"Yang Sai","labelTh":"ยางซ้าย"},{"code":"640106บ้านกล้วย","labelEn":"Ban Kluai","labelTh":"บ้านกล้วย"},{"code":"640107บ้านหลุม","labelEn":"บ้านหลุม","labelTh":"บ้านหลุม"},{"code":"640108ตาลเตี้ย","labelEn":"ตาลเตี้ย","labelTh":"ตาลเตี้ย"},{"code":"640109ปากพระ","labelEn":"Pak Phra","labelTh":"ปากพระ"},{"code":"640110วังทองแดง","labelEn":"วังทองแดง","labelTh":"วังทองแดง"}]},{"code":"6402บ้านด่านลานหอย","labelEn":"Ban Dan Lan Hoi","labelTh":"บ้านด่านลานหอย","postalCodes":["64140"],"subDistricts":[{"code":"640203วังตะคร้อ","labelEn":"Wang Takhro","labelTh":"วังตะคร้อ"},{"code":"640204วังน้ำขาว","labelEn":"วังน้ำขาว","labelTh":"วังน้ำขาว"},{"code":"640205ตลิ่งชัน","labelEn":"Taling Chan","labelTh":"ตลิ่งชัน"},{"code":"640206หนองหญ้าปล้อง","labelEn":"Nong Ya Plong","labelTh":"หนองหญ้าปล้อง"},{"code":"640201ลานหอย","labelEn":"Lan Hoi","labelTh":"ลานหอย"},{"code":"640202บ้านด่าน","labelEn":"บ้านด่าน","labelTh":"บ้านด่าน"},{"code":"640207วังลึก","labelEn":"Wang Luek","labelTh":"วังลึก"}]},{"code":"6403คีรีมาศ","labelEn":"Khiri Mat","labelTh":"คีรีมาศ","postalCodes":["64160"],"subDistricts":[{"code":"640301โตนด","labelEn":"Tanot","labelTh":"โตนด"},{"code":"640302ทุ่งหลวง","labelEn":"Thung Luang","labelTh":"ทุ่งหลวง"},{"code":"640303บ้านป้อม","labelEn":"บ้านป้อม","labelTh":"บ้านป้อม"},{"code":"640304สามพวง","labelEn":"Sam Phuang","labelTh":"สามพวง"},{"code":"640305ศรีคีรีมาศ","labelEn":"ศรีคีรีมาศ","labelTh":"ศรีคีรีมาศ"},{"code":"640306หนองจิก","labelEn":"Nong Chik","labelTh":"หนองจิก"},{"code":"640307นาเชิงคีรี","labelEn":"นาเชิงคีรี","labelTh":"นาเชิงคีรี"},{"code":"640308หนองกระดิ่ง","labelEn":"Nong Krading","labelTh":"หนองกระดิ่ง"},{"code":"640309บ้านน้ำพุ","labelEn":"บ้านน้ำพุ","labelTh":"บ้านน้ำพุ"},{"code":"640310ทุ่งยางเมือง","labelEn":"ทุ่งยางเมือง","labelTh":"ทุ่งยางเมือง"}]},{"code":"6404กงไกรลาศ","labelEn":"Kong Krailat","labelTh":"กงไกรลาศ","postalCodes":["64170"],"subDistricts":[{"code":"640411บ้านใหม่สุขเกษม","labelEn":"บ้านใหม่สุขเกษม","labelTh":"บ้านใหม่สุขเกษม"},{"code":"640408กกแรต","labelEn":"Kok Raet","labelTh":"กกแรต"},{"code":"640409ท่าฉนวน","labelEn":"Tha Chanuan","labelTh":"ท่าฉนวน"},{"code":"640410หนองตูม","labelEn":"Nong Tum","labelTh":"หนองตูม"},{"code":"640401กง","labelEn":"Kong","labelTh":"กง"},{"code":"640402บ้านกร่าง","labelEn":"Ban Krang","labelTh":"บ้านกร่าง"},{"code":"640403ไกรนอก","labelEn":"Krai Nok","labelTh":"ไกรนอก"},{"code":"640404ไกรกลาง","labelEn":"ไกรกลาง","labelTh":"ไกรกลาง"},{"code":"640405ไกรใน","labelEn":"Krai Nai","labelTh":"ไกรใน"},{"code":"640406ดงเดือย","labelEn":"Dong Dueai","labelTh":"ดงเดือย"},{"code":"640407ป่าแฝก","labelEn":"Pa Faek","labelTh":"ป่าแฝก"}]},{"code":"6405ศรีสัชนาลัย","labelEn":"ศรีสัชนาลัย","labelTh":"ศรีสัชนาลัย","postalCodes":["64130","64190"],"subDistricts":[{"code":"640511สารจิตร","labelEn":"San Chit","labelTh":"สารจิตร"},{"code":"640505บ้านตึก","labelEn":"Ban Tuek","labelTh":"บ้านตึก"},{"code":"640506หนองอ้อ","labelEn":"Nong O","labelTh":"หนองอ้อ"},{"code":"640507ท่าชัย","labelEn":"ท่าชัย","labelTh":"ท่าชัย"},{"code":"640508ศรีสัชนาลัย","labelEn":"ศรีสัชนาลัย","labelTh":"ศรีสัชนาลัย"},{"code":"640509ดงคู่","labelEn":"Dong Khu","labelTh":"ดงคู่"},{"code":"640510บ้านแก่ง","labelEn":"บ้านแก่ง","labelTh":"บ้านแก่ง"},{"code":"640501หาดเสี้ยว","labelEn":"หาดเสี้ยว","labelTh":"หาดเสี้ยว"},{"code":"640502ป่างิ้ว","labelEn":"Pa Ngio","labelTh":"ป่างิ้ว"},{"code":"640503แม่สำ","labelEn":"แม่สำ","labelTh":"แม่สำ"},{"code":"640504แม่สิน","labelEn":"Mae Sin","labelTh":"แม่สิน"}]},{"code":"6406ศรีสำโรง","labelEn":"Si Samrong","labelTh":"ศรีสำโรง","postalCodes":["64120"],"subDistricts":[{"code":"640601คลองตาล","labelEn":"Khlong Tan","labelTh":"คลองตาล"},{"code":"640602วังลึก","labelEn":"Wang Luek","labelTh":"วังลึก"},{"code":"640603สามเรือน","labelEn":"สามเรือน","labelTh":"สามเรือน"},{"code":"640604บ้านนา","labelEn":"Ban Na","labelTh":"บ้านนา"},{"code":"640605วังทอง","labelEn":"Wang Thong","labelTh":"วังทอง"},{"code":"640606นาขุนไกร","labelEn":"Na Khun Krai","labelTh":"นาขุนไกร"},{"code":"640607เกาะตาเลี้ยง","labelEn":"Ko Ta Liang","labelTh":"เกาะตาเลี้ยง"},{"code":"640608วัดเกาะ","labelEn":"Wat Ko","labelTh":"วัดเกาะ"},{"code":"640613ราวต้นจันทร์","labelEn":"Rao Ton Chan","labelTh":"ราวต้นจันทร์"},{"code":"640609บ้านไร่","labelEn":"Ban Rai","labelTh":"บ้านไร่"},{"code":"640610ทับผึ้ง","labelEn":"ทับผึ้ง","labelTh":"ทับผึ้ง"},{"code":"640611บ้านซ่าน","labelEn":"Ban San","labelTh":"บ้านซ่าน"},{"code":"640612วังใหญ่","labelEn":"Wang Yai","labelTh":"วังใหญ่"}]},{"code":"6407สวรรคโลก","labelEn":"Sawankhalok","labelTh":"สวรรคโลก","postalCodes":["64110"],"subDistricts":[{"code":"640707นาทุ่ง","labelEn":"นาทุ่ง","labelTh":"นาทุ่ง"},{"code":"640708คลองยาง","labelEn":"Khlong Yang","labelTh":"คลองยาง"},{"code":"640709เมืองบางยม","labelEn":"Mueang Bang Yom","labelTh":"เมืองบางยม"},{"code":"640710ท่าทอง","labelEn":"ท่าทอง","labelTh":"ท่าทอง"},{"code":"640711ปากน้ำ","labelEn":"Pak Nam","labelTh":"ปากน้ำ"},{"code":"640712ป่ากุมเกาะ","labelEn":"Pa Kum Ko","labelTh":"ป่ากุมเกาะ"},{"code":"640713เมืองบางขลัง","labelEn":"Mueang Bang Khlang","labelTh":"เมืองบางขลัง"},{"code":"640714หนองกลับ","labelEn":"Nong Klap","labelTh":"หนองกลับ"},{"code":"640701เมืองสวรรคโลก","labelEn":"Mueang Sawankhalok","labelTh":"เมืองสวรรคโลก"},{"code":"640702ในเมือง","labelEn":"ในเมือง","labelTh":"ในเมือง"},{"code":"640703คลองกระจง","labelEn":"Khlong Krachong","labelTh":"คลองกระจง"},{"code":"640704วังพิณพาทย์","labelEn":"Wang Phinphat","labelTh":"วังพิณพาทย์"},{"code":"640705วังไม้ขอน","labelEn":"Wang Mai Khon","labelTh":"วังไม้ขอน"},{"code":"640706ย่านยาว","labelEn":"Yan Yao","labelTh":"ย่านยาว"}]},{"code":"6408ศรีนคร","labelEn":"ศรีนคร","labelTh":"ศรีนคร","postalCodes":["64180"],"subDistricts":[{"code":"640801ศรีนคร","labelEn":"Si Nakhon","labelTh":"ศรีนคร"},{"code":"640802นครเดิฐ","labelEn":"Nakhon Doet","labelTh":"นครเดิฐ"},{"code":"640803น้ำขุม","labelEn":"Nam Khum","labelTh":"น้ำขุม"},{"code":"640804คลองมะพลับ","labelEn":"Khlong Maphlap","labelTh":"คลองมะพลับ"},{"code":"640805หนองบัว","labelEn":"Nong Bua","labelTh":"หนองบัว"}]},{"code":"6409ทุ่งเสลี่ยม","labelEn":"Thung Saliam","labelTh":"ทุ่งเสลี่ยม","postalCodes":["64150","64230"],"subDistricts":[{"code":"640901บ้านใหม่ไชยมงคล","labelEn":"Ban Mai Chai Mongkhon","labelTh":"บ้านใหม่ไชยมงคล"},{"code":"640902ไทยชนะศึก","labelEn":"Thai Chana Suek","labelTh":"ไทยชนะศึก"},{"code":"640903ทุ่งเสลี่ยม","labelEn":"Thung Saliam","labelTh":"ทุ่งเสลี่ยม"},{"code":"640904กลางดง","labelEn":"Klang Dong","labelTh":"กลางดง"},{"code":"640905เขาแก้วศรีสมบูรณ์","labelEn":"Khao Kaeo Si Sombun","labelTh":"เขาแก้วศรีสมบูรณ์"}]}]}